setup.cfg
setup.py
Simple_Menus.egg-info/PKG-INFO
Simple_Menus.egg-info/SOURCES.txt
Simple_Menus.egg-info/dependency_links.txt
Simple_Menus.egg-info/requires.txt
Simple_Menus.egg-info/top_level.txt
simplemenus/__init__.py
simplemenus/smenus.py