Metadata-Version: 1.1
Name: Simple-Menus
Version: 0.5.1
Summary: Simple ASCII menus for humans.
Home-page: https://github.com/gpalsingh/Simple-Menus
Author: Gurkirpal Singh
Author-email: gurkirpal204@gmail.com
License: UNKNOWN
Download-URL: https://github.com/gpalsingh/Simple-Menus/tarball/0.5.0
Keywords: menus,ascii,interactive,configurable,smart
Platform: UNKNOWN
